reproduce/__init__.py
reproduce/reproduce.py
reproduce/utils.py
reproduce-0.0.10.dist-info/METADATA
reproduce-0.0.10.dist-info/WHEEL
reproduce-0.0.10.dist-info/top_level.txt
reproduce-0.0.10.dist-info/RECORD
