Metadata-Version: 2.1
Name: reproduce
Version: 0.0.10
Summary: Computational reproduction library.
Home-page: https://bitbucket.org/natcap/reproduce
Maintainer: Rich Sharp
Maintainer-email: richpsharp@gmail.com
License: BSD
Keywords: computing reproduction
Platform: UNKNOWN
Classifier: Intended Audience :: Developers
Classifier: Natural Language :: English
Classifier: Operating System :: MacOS :: MacOS X
Classifier: Operating System :: Microsoft
Classifier: Operating System :: POSIX
Classifier: Programming Language :: Python :: 3.6
Classifier: License :: OSI Approved :: BSD License
Requires-Dist: google-cloud
Requires-Dist: crcmod
